mathematical/__init__.py
mathematical/data_frames.py
mathematical/linear_regression.py
mathematical/outliers.py
mathematical/py.typed
mathematical/stats.py
mathematical/utils.py
mathematical-0.5.1.post1.dist-info/LICENSE
mathematical-0.5.1.post1.dist-info/METADATA
mathematical-0.5.1.post1.dist-info/WHEEL
mathematical-0.5.1.post1.dist-info/entry_points.txt
mathematical-0.5.1.post1.dist-info/RECORD
