Metadata-Version: 2.1
Name: mathematical
Version: 0.5.1.post1
Summary: Mathematical tools for Python 📐 🐍 🛠️
Author-email: Dominic Davis-Foster <dominic@davis-foster.co.uk>
License: LGPL-3.0-or-later
Keywords: mathematics,utilities
Home-page: https://github.com/domdfcoding/mathematical
Project-URL: Issue Tracker, https://github.com/domdfcoding/mathematical/issues
Project-URL: Source Code, https://github.com/domdfcoding/mathematical
Project-URL: Documentation, https://mathematical.readthedocs.io/en/latest
Platform: Windows
Platform: macOS
Platform: Linux
Classifier: Development Status :: 4 - Beta
Classifier: Intended Audience :: Developers
Classifier: Intended Audience :: Education
Classifier: Intended Audience :: End Users/Desktop
Classifier: Intended Audience :: Science/Research
Classifier: License :: OSI Approved :: GNU Lesser General Public License v3 or later (LGPLv3+)
Classifier: Operating System :: OS Independent
Classifier: Programming Language :: Python
Classifier: Programming Language :: Python :: 3 :: Only
Classifier: Programming Language :: Python :: 3.6
Classifier: Programming Language :: Python :: 3.7
Classifier: Programming Language :: Python :: 3.8
Classifier: Programming Language :: Python :: 3.9
Classifier: Programming Language :: Python :: 3.10
Classifier: Programming Language :: Python :: 3.11
Classifier: Programming Language :: Python :: 3.12
Classifier: Programming Language :: Python :: Implementation :: CPython
Classifier: Topic :: Software Development :: Libraries :: Python Modules
Classifier: Typing :: Typed
Requires-Python: >=3.6
Requires-Dist: domdf-python-tools>=2.7.0
Requires-Dist: numpy>=1.19.1; platform_system != "Windows"
Requires-Dist: numpy!=1.19.4,>=1.19.3; platform_system == "Windows"
Requires-Dist: pandas>=1.0.1
Requires-Dist: typing-extensions>=3.7.4.3
